{
  "collection": "directus_sync_id_map",
  "field": "local_id",
  "type": "string",
  "meta": null,
  "schema": {
    "name": "local_id",
    "table": "directus_sync_id_map",
    "data_type": "varchar",
    "default_value": null,
    "max_length": 255,
    "numeric_precision": null,
    "numeric_scale": null,
    "is_nullable": false,
    "is_unique": false,
    "is_primary_key": false,
    "is_generated": false,
    "generation_expression": null,
    "has_auto_increment": false,
    "foreign_key_table": null,
    "foreign_key_column": null
  }
}
